biolmai/__init__.py
biolmai/api.py
biolmai/asynch.py
biolmai/auth.py
biolmai/biolmai.py
biolmai/cli.py
biolmai/client.py
biolmai/cls.py
biolmai/const.py
biolmai/ltc.py
biolmai/payloads.py
biolmai/seqflow_auth.py
biolmai/validate.py
biolmai-0.2.15.dist-info/licenses/AUTHORS.rst
biolmai-0.2.15.dist-info/licenses/LICENSE
biolmai-0.2.15.dist-info/METADATA
biolmai-0.2.15.dist-info/WHEEL
biolmai-0.2.15.dist-info/entry_points.txt
biolmai-0.2.15.dist-info/top_level.txt
biolmai-0.2.15.dist-info/RECORD
