Metadata-Version: 2.4
Name: biolmai
Version: 0.2.15
Summary: BioLM Python client
Home-page: https://github.com/BioLM/py-biolm
Author: BioLM
Author-email: BioLM <support@biolm.ai>
License: Apache Software License 2.0
Keywords: biolmai
Classifier: Development Status :: 2 - Pre-Alpha
Classifier: Intended Audience :: Developers
Classifier: License :: OSI Approved :: Apache Software License
Classifier: Natural Language :: English
Classifier: Programming Language :: Python :: 3
Classifier: Programming Language :: Python :: 3.8
Classifier: Programming Language :: Python :: 3.9
Classifier: Programming Language :: Python :: 3.10
Classifier: Programming Language :: Python :: 3.11
Classifier: Programming Language :: Python :: 3.12
Classifier: Programming Language :: Python :: 3.13
Requires-Python: >=3.7
License-File: LICENSE
License-File: AUTHORS.rst
Requires-Dist: httpx>=0.23.0
Requires-Dist: httpcore
Requires-Dist: Click>=6.0
Requires-Dist: requests
Requires-Dist: aiodns
Requires-Dist: synchronicity>=0.5.0; python_version >= "3.9"
Requires-Dist: synchronicity<0.5.0; python_version < "3.9"
Requires-Dist: typing_extensions; python_version < "3.9"
Requires-Dist: aiohttp<=3.8.6; python_version < "3.12"
Requires-Dist: aiohttp>=3.9.0; python_version >= "3.12"
Requires-Dist: async-lru
Requires-Dist: aiofiles
Requires-Dist: cryptography
Requires-Dist: h2
Requires-Dist: nest_asyncio
Dynamic: author
Dynamic: home-page
Dynamic: license-file
Dynamic: requires-python
